fileai/__init__.py
fileai/file_manager.py
filely/__init__.py
filely/file.py
fileai-0.1.dist-info/METADATA
fileai-0.1.dist-info/WHEEL
fileai-0.1.dist-info/entry_points.txt
fileai-0.1.dist-info/top_level.txt
fileai-0.1.dist-info/RECORD
